bonbast/__init__.py
bonbast/__main__.py
bonbast/main.py
bonbast/server.py
bonbast/tables.py
bonbast/helpers/__init__.py
bonbast/helpers/click_callbacks.py
bonbast/helpers/currency_flags.py
bonbast/helpers/utils.py
bonbast/managers/__init__.py
bonbast/managers/storage_manager.py
bonbast/managers/token_manager.py
bonbast/models/__init__.py
bonbast/models/coin.py
bonbast/models/currency.py
bonbast/models/gold.py
bonbast/models/graph.py
bonbast/models/token.py
bonbast-1.0.2.dist-info/LICENSE
bonbast-1.0.2.dist-info/METADATA
bonbast-1.0.2.dist-info/WHEEL
bonbast-1.0.2.dist-info/entry_points.txt
bonbast-1.0.2.dist-info/top_level.txt
bonbast-1.0.2.dist-info/RECORD
