Metadata-Version: 2.1
Name: bonbast
Version: 1.0.2
Summary: Get currencies exchange rates for IRR from Bonbast.com
Author-email: Amir Hossein SamadiPour <samadipoor2@gmail.com>, Alireza Azadi <alireza_azadi@hotmail.com>, Iliya Aghamajidi <dozheiny@gmail.com>, Parsa Shahmaleki <parsampsh@gmail.com>
License: MIT License
Project-URL: repository, https://github.com/SamadiPour/bonbast
Keywords: bonbast,IRR Exchange rates
Classifier: License :: OSI Approved :: MIT License
Classifier: Programming Language :: Python
Classifier: Programming Language :: Python :: 3
Requires-Python: >=3.7
License-File: LICENSE
Requires-Dist: requests >=2.28.0
Requires-Dist: rich >=12.4.4
Requires-Dist: beautifulsoup4 >=4.11.1
Requires-Dist: bs4
Requires-Dist: click >=8.1.3
Provides-Extra: build
Requires-Dist: build ; extra == 'build'
Requires-Dist: twine ; extra == 'build'
Requires-Dist: bumpver ; extra == 'build'
